sabbath_school_lessons/PDFGenerator.py
sabbath_school_lessons/__init__.py
sabbath_school_lessons/batch.py
sabbath_school_lessons/booklets.py
sabbath_school_lessons/cms.py
sabbath_school_lessons/flowables.py
sabbath_school_lessons/markdown.py
sabbath_school_lessons/translations.py
sabbath_school_lessons/fonts/Arial-Bold.ttf
sabbath_school_lessons-0.1.5.dist-info/LICENSE
sabbath_school_lessons-0.1.5.dist-info/METADATA
sabbath_school_lessons-0.1.5.dist-info/WHEEL
sabbath_school_lessons-0.1.5.dist-info/top_level.txt
sabbath_school_lessons-0.1.5.dist-info/RECORD
