Metadata-Version: 2.1
Name: sabbath_school_lessons
Version: 0.1.5
Summary: Python module for processing sabbath school bible study guides
Home-page: https://sabbathschool.github.io
Author: Brian Onang'o
Author-email: surgbc@gmail.com
Project-URL: Homepage, https://github.com/SabbathSchool/sabbath_school_lessons
Project-URL: Issues, https://github.com/SabbathSchool/sabbath_school_lessons/issues
Classifier: Programming Language :: Python :: 3
Classifier: License :: OSI Approved :: Apache Software License
Classifier: Operating System :: OS Independent
Requires-Python: >=3.8
License-File: LICENSE
Requires-Dist: beautifulsoup4
Requires-Dist: bs4
Requires-Dist: chardet
Requires-Dist: Markdown
Requires-Dist: pillow
Requires-Dist: PyPDF2
Requires-Dist: reportlab
Requires-Dist: soupsieve
